MolDes/CM_util.py
MolDes/GCT_util.py
MolDes/__init__.py
MolDes-0.0.3.dist-info/METADATA
MolDes-0.0.3.dist-info/WHEEL
MolDes-0.0.3.dist-info/top_level.txt
MolDes-0.0.3.dist-info/RECORD
